aidios_sdk/__init__.py
aidios_sdk-0.2.dist-info/METADATA
aidios_sdk-0.2.dist-info/WHEEL
aidios_sdk-0.2.dist-info/top_level.txt
aidios_sdk-0.2.dist-info/RECORD
