Metadata-Version: 2.1
Name: aidios-sdk
Version: 0.2
Summary: SDK for the Aidios API
Home-page: https://aidios.co.uk
Author: Jamie Gilchrist
Author-email: jamie.gilchrist@tunestamp.com
License: UNKNOWN
Platform: UNKNOWN
Requires-Dist: requests
